Metadata-Version: 1.0
Name: daily-report
Version: 2.6
Summary: A package for the production of daily and cumulative reports attached to PyBpod tasks.
Home-page: https://bitbucket.org/AFont33/daily_reports/
Author: Albert Font
Author-email: albertf80@gmail.com
License: UNKNOWN
Platform: UNKNOWN
